aedev/tpl_namespace_root/__init__.py
aedev/tpl_namespace_root/templates/de_otf_de_tpl_README.md
aedev/tpl_namespace_root/templates/de_mtp_templates/de_otf_de_spt_namespace-root_de_otf_de_tpl_README.md
aedev/tpl_namespace_root/templates/de_sfp_docs/de_otf_de_tpl_index.rst
aedev/tpl_namespace_root/templates/de_sfp_docs/features_and_examples.rst
aedev_tpl_namespace_root-0.3.14.dist-info/LICENSE.md
aedev_tpl_namespace_root-0.3.14.dist-info/METADATA
aedev_tpl_namespace_root-0.3.14.dist-info/WHEEL
aedev_tpl_namespace_root-0.3.14.dist-info/top_level.txt
aedev_tpl_namespace_root-0.3.14.dist-info/RECORD
